molmetrics/__init__.py
molmetrics/__main__.py
molmetrics/_version.py
molmetrics/geometry.py
molmetrics/io.py
molmetrics/mol_describe.py
molmetrics/py.typed
molmetrics/qed.py
molmetrics/util.py
molmetrics/tests/__init__.py
molmetrics/tests/test_geometry.py
molmetrics/tests/test_integration.py
molmetrics/tests/test_io.py
molmetrics/tests/test_molmetrics.py
molmetrics/tests/test_qed.py
molmetrics/tests/test_util.py
molmetrics-1.0.1.dist-info/licenses/LICENSE
molmetrics-1.0.1.dist-info/METADATA
molmetrics-1.0.1.dist-info/WHEEL
molmetrics-1.0.1.dist-info/entry_points.txt
molmetrics-1.0.1.dist-info/top_level.txt
molmetrics-1.0.1.dist-info/RECORD
