Metadata-Version: 2.4
Name: molmetrics
Version: 1.0.1
Summary: A package for calculating QED scores, molecular descriptors, and optimized geometry descriptors for libraries of small molecules.
Author-email: "Seth D. Veenbaas" <sdveenbaas@gmail.com>
License: BSD-3-Clause
Project-URL: Homepage, https://github.com/Weeks-UNC/molmetrics
Project-URL: Documentation, https://github.com/Weeks-UNC/molmetrics
Project-URL: Source, https://github.com/Weeks-UNC/molmetrics
Project-URL: Issues, https://github.com/Weeks-UNC/molmetrics/issues
Classifier: License :: OSI Approved :: BSD License
Classifier: Programming Language :: Python :: 3
Classifier: Programming Language :: Python :: 3.8
Classifier: Programming Language :: Python :: 3.9
Classifier: Programming Language :: Python :: 3.10
Classifier: Programming Language :: Python :: 3.11
Classifier: Operating System :: OS Independent
Requires-Python: >=3.10
License-File: LICENSE
Requires-Dist: rdkit>=2025.03.2
Requires-Dist: pandas
Requires-Dist: openpyxl
Requires-Dist: numpy
Requires-Dist: importlib-resources; python_version < "3.10"
Requires-Dist: argparse; python_version < "3.7"
Provides-Extra: test
Requires-Dist: pytest; extra == "test"
Requires-Dist: pytest-cov; extra == "test"
Provides-Extra: docs
Requires-Dist: sphinx; extra == "docs"
Requires-Dist: sphinx-autodoc-typehints; extra == "docs"
Requires-Dist: sphinx-copybutton; extra == "docs"
Requires-Dist: sphinx-design; extra == "docs"
Requires-Dist: pydata-sphinx-theme; extra == "docs"
Dynamic: license-file
